grailabsDataCli/__init__.py
grailabsDataCli/automation_interface.py
grailabsDataCli/extend_job.py
grailabsDataCli/new_job.py
grailabsDataCli/scripts/__init__.py
grailabsDataCli/scripts/apiHandler.py
grailabsDataCli/scripts/appLogger.py
grailabsDataCli/scripts/authHandler.py
grailabsDataCli/scripts/automationClient.py
grailabsDataCli/scripts/descriptionVerifier.py
grailabsDataCli/scripts/jobBuilder.py
grailabsDataCliLib-1.0.0.dist-info/METADATA
grailabsDataCliLib-1.0.0.dist-info/WHEEL
grailabsDataCliLib-1.0.0.dist-info/top_level.txt
grailabsDataCliLib-1.0.0.dist-info/RECORD
