Metadata-Version: 2.1
Name: grailabsDataCliLib
Version: 1.0.0
Summary: A example Python package
Home-page: https://github.com/daniELgrailDev/grailabs-data-cli
Author: Daniel Zelalem
Author-email: danielzelalemheru@gmail.com
License: BSD 2-clause
Platform: UNKNOWN
Classifier: License :: OSI Approved :: BSD License
Classifier: Operating System :: POSIX :: Linux
Classifier: Programming Language :: Python :: 2
Classifier: Programming Language :: Python :: 2.7
Classifier: Programming Language :: Python :: 3
Classifier: Programming Language :: Python :: 3.4
Classifier: Programming Language :: Python :: 3.5
Requires-Dist: requests (==2.27.1)
